MANIFEST.in
README.md
requirements.txt
setup.py
joker/redis/__init__.py
joker/redis/error.py
joker/redis/extended.py
joker/redis/loggers.py
joker/redis/notification.py
joker_redis.egg-info/PKG-INFO
joker_redis.egg-info/SOURCES.txt
joker_redis.egg-info/dependency_links.txt
joker_redis.egg-info/namespace_packages.txt
joker_redis.egg-info/not-zip-safe
joker_redis.egg-info/requires.txt
joker_redis.egg-info/top_level.txt