Metadata-Version: 2.1
Name: joker-redis
Version: 0.0.3
Summary: redis based utilities
Home-page: https://github.com/frozflame/joker-redis
Author: frozflame
Author-email: frozflame@outlook.com
License: GNU General Public License (GPL)
Platform: UNKNOWN
Classifier: Programming Language :: Python
Classifier: Programming Language :: Python :: 3
Classifier: Programming Language :: Python :: 3.4
Classifier: Programming Language :: Python :: 3.5
Classifier: Programming Language :: Python :: 3.6
Classifier: Programming Language :: Python :: 3.7
Classifier: Programming Language :: Python :: 3.8
Classifier: Programming Language :: Python :: 3.9
Classifier: Programming Language :: Python :: 3.10
